text_augmentation/__init__.py
text_augmentation/data_augmentation.py
text_augmentation/download_wordnet.py
text_augmentation/wordnet_augmentation.py
text_augmentation-2021.1.dist-info/LICENSE
text_augmentation-2021.1.dist-info/WHEEL
text_augmentation-2021.1.dist-info/METADATA
text_augmentation-2021.1.dist-info/RECORD
